Metadata-Version: 1.0
Name: pythoscope
Version: 0.4.3
Summary: unit test generator for Python
Home-page: http://pythoscope.org
Author: Michal Kwiatkowski
Author-email: constant.beta@gmail.com
License: MIT
Platform: UNKNOWN
Classifier: Development Status :: 3 - Alpha
Classifier: Environment :: Console
Classifier: Intended Audience :: Developers
Classifier: Programming Language :: Python
Classifier: Topic :: Software Development :: Code Generators
Classifier: Topic :: Software Development :: Testing
